<?xml version="1.0" encoding="utf-8" ?>
<hibernate-mapping xmlns="urn:nhibernate-mapping-2.2" assembly="Hulen.Storage" namespace="Hulen.Storage.DTO">

  <class name="Hulen.Storage.DTO.FixedArrangementCostsDTO, Hulen.Storage" table="FixedArrangementCosts" lazy="false">
    <id name ="Id" column="Id"/>
    <property name="Name" column="Name" />
    <property name="GeneratedDate" column="GeneratedDate" />
    <property name="PricePerBeer" column="PricePerBeer" />
    <property name="PricePerWine" column="PricePerWine" />
    <property name="FixedTechRental" column="FixedTechRental" />
    <property name="SoundmanSalery" column="SoundmanSalery" />
    <property name="SoundmanSaleryPerWarmUp" column="SoundmanSaleryPerWarmUp" />
    <property name="PromotionExpences" column="PromotionExpences" />
    <property name="FixedCosts" column="FixedCosts" />
    <property name="DocumentId" column="DocumentId" />
  </class>
</hibernate-mapping>
